setup.py
oioswift/__init__.py
oioswift/server.py
oioswift/utils.py
oioswift.egg-info/PKG-INFO
oioswift.egg-info/SOURCES.txt
oioswift.egg-info/dependency_links.txt
oioswift.egg-info/entry_points.txt
oioswift.egg-info/pbr.json
oioswift.egg-info/requires.txt
oioswift.egg-info/top_level.txt
oioswift/proxy/__init__.py
oioswift/proxy/controllers/__init__.py
oioswift/proxy/controllers/account.py
oioswift/proxy/controllers/base.py
oioswift/proxy/controllers/container.py
oioswift/proxy/controllers/obj.py