Metadata-Version: 1.1
Name: oioswift
Version: 0.4.0
Summary: OpenIO Swift Gateway
Home-page: https://github.com/open-io/oio-swift
Author: OpenIO
Author-email: support@openio.io
License: Apache License (2.0)
Platform: UNKNOWN
Classifier: Development Status :: 3 - Alpha
Classifier: Programming Language :: Python :: 2.7
Classifier: License :: OSI Approved :: Apache Software License
Classifier: Intended Audience :: Information Technology
Classifier: Operating System :: OS Independent
